KnowledgeIngestor/__init__.py
KnowledgeIngestor/ingestor.py
KnowledgeIngestor/core/__init__.py
KnowledgeIngestor/core/nodes.py
KnowledgeIngestor/core/parsers.py
knowledgeingestor-0.1.2.dist-info/METADATA
knowledgeingestor-0.1.2.dist-info/WHEEL
knowledgeingestor-0.1.2.dist-info/top_level.txt
knowledgeingestor-0.1.2.dist-info/RECORD
